letmego/__init__.py
letmego/conf.py
letmego-2023.10.16.dist-info/METADATA
letmego-2023.10.16.dist-info/WHEEL
letmego-2023.10.16.dist-info/licenses/LICENSE
letmego-2023.10.16.dist-info/licenses/NOTICE
letmego-2023.10.16.dist-info/RECORD
