Metadata-Version: 2.1
Name: letmego
Version: 2023.10.16
Summary: letmego
Project-URL: Source, https://github.com/linuxdeepin/linuxdeepin
Project-URL: Documentation, https://linuxdeepin.github.io/letmego
Author-email: mikigo <huangmingqiang@uniontech.com>
License-File: LICENSE
License-File: NOTICE
Classifier: License :: OSI Approved :: Apache Software License
Classifier: Operating System :: OS Independent
Classifier: Programming Language :: Python :: 3
Requires-Python: >=3.7
Provides-Extra: doc
Requires-Dist: mkdocs-material; extra == 'doc'
Provides-Extra: test
Requires-Dist: pytest; extra == 'test'
